data/__init__.py
data/kor_coordinates.txt
naverplacescraper/__init__.py
naverplacescraper/coordinates.py
naverplacescraper/httprequest.py
naverplacescraper/naverplace.py
naverplacescraper/utils.py
naverplacescraper-1.0.0.dist-info/LICENSE
naverplacescraper-1.0.0.dist-info/METADATA
naverplacescraper-1.0.0.dist-info/WHEEL
naverplacescraper-1.0.0.dist-info/top_level.txt
naverplacescraper-1.0.0.dist-info/RECORD
