Metadata-Version: 2.1
Name: naverplacescraper
Version: 1.0.0
Summary: Scrapes text data about the store/company from Naver Place.
Home-page: UNKNOWN
Author: Choi Jiwoo
Author-email: cho2.jiwoo@gmail.com
License: MIT
Project-URL: Source, https://github.com/choi-jiwoo/naver-place-scraper
Keywords: python,sns,scraper,crawler
Platform: UNKNOWN
Classifier: Development Status :: 3 - Alpha
Classifier: Intended Audience :: Education
Classifier: Programming Language :: Python
Classifier: License :: OSI Approved :: MIT License
Classifier: Operating System :: OS Independent
Requires-Dist: pandas (>=1.3.3)
Requires-Dist: requests (>=2.26.0)
Requires-Dist: importlib-resources (>=5.4.0)
